zuper_ide_imp/__init__.py
zuper_ide_imp/cde_view.py
zuper_ide_imp/create_test_cases.py
zuper_ide_imp/fsread_fs.py
zuper_ide_imp/fsread_git.py
zuper_ide_imp/fsread_github.py
zuper_ide_imp/fsread_github_fs.py
zuper_ide_imp/listen_branch_fs_main.py
zuper_ide_imp/loader_imp.py
zuper_ide_imp/localcde.py
zuper_ide_imp/mcdp_repo_load_all.py
zuper_ide_imp/mcdp_view.py
zuper_ide_imp/mcdp_view_cde.py
zuper_ide_imp/py.typed
zuper_ide_imp/thing_computation.py
zuper_ide_imp/utils.py
zuper_ide_imp/visualization_proxies.py
zuper_ide_imp/visualizations.py
zuper_ide_imp_z7-7.3.2404191145.dist-info/METADATA
zuper_ide_imp_z7-7.3.2404191145.dist-info/WHEEL
zuper_ide_imp_z7-7.3.2404191145.dist-info/entry_points.txt
zuper_ide_imp_z7-7.3.2404191145.dist-info/top_level.txt
zuper_ide_imp_z7-7.3.2404191145.dist-info/zip-safe
zuper_ide_imp_z7-7.3.2404191145.dist-info/RECORD
